{
    "meta": {
        "filename": "wiki_1852 сон.json",
        "title": "1852 сон",
        "author": "",
        "year": "2022",
        "recplace": "",
        "genre": "nonfiction"
    },
    "sentences": [
        {
            "text": "ТӀоцебе центиллион абураб тарих хӀалтӀизабуна .",
            "words": [
                {
                    "wf": "ТӀоцебе",
                    "wtype": "word",
                    "off_start": 0,
                    "off_end": 7,
                    "next_word": 1,
                    "sentence_index": 0,
                    "sentence_index_neg": 5,
                    "ana": [
                        {
                            "lex": "тӏоцебе",
                            "trans_ru": "впервые",
                            "gr.case": "all",
                            "gr.gender": "nt",
                            "gr.pos": "adv"
                        }
                    ]
                },
                {
                    "wf": "центиллион",
                    "wtype": "word",
                    "off_start": 8,
                    "off_end": 18,
                    "next_word": 2,
                    "sentence_index": 1,
                    "sentence_index_neg": 4
                },
                {
                    "wf": "абураб",
                    "wtype": "word",
                    "off_start": 19,
                    "off_end": 25,
                    "next_word": 3,
                    "sentence_index": 2,
                    "sentence_index_neg": 3,
                    "ana": [
                        {
                            "lex": "абизе",
                            "trans_ru": "сказать",
                            "gr.v_form_ptcp": "gpr2",
                            "gr.gender": "nt",
                            "gr.transitivity": "tv",
                            "gr.pos": "vblex"
                        }
                    ]
                },
                {
                    "wf": "тарих",
                    "wtype": "word",
                    "off_start": 26,
                    "off_end": 31,
                    "next_word": 4,
                    "sentence_index": 3,
                    "sentence_index_neg": 2,
                    "ana": [
                        {
                            "lex": "тарих",
                            "trans_ru": "история",
                            "gr.case": "nom",
                            "gr.num": "sg",
                            "gr.gender": "nt",
                            "gr.pos": "n"
                        }
                    ]
                },
                {
                    "wf": "хӀалтӀизабуна",
                    "wtype": "word",
                    "off_start": 32,
                    "off_end": 45,
                    "next_word": 5,
                    "sentence_index": 4,
                    "sentence_index_neg": 1,
                    "ana": [
                        {
                            "lex": "хӏалтӏизабизе",
                            "trans_ru": "дать",
                            "gr.tense": "past",
                            "gr.gender": "nt",
                            "gr.transitivity": "tv",
                            "gr.pos": "vblex"
                        }
                    ]
                },
                {
                    "wf": ".",
                    "wtype": "punct",
                    "off_start": 46,
                    "off_end": 47,
                    "next_word": null
                }
            ],
            "lang": 0
        },
        {
            "text": "25 июн — Антонио Гауди , испан архитектор ( хв .",
            "words": [
                {
                    "wf": "25",
                    "wtype": "word",
                    "off_start": 0,
                    "off_end": 2,
                    "next_word": 1,
                    "sentence_index": 0,
                    "sentence_index_neg": 9,
                    "ana": [
                        {
                            "lex": "25",
                            "trans_ru": "25",
                            "gr.pos": "num"
                        }
                    ]
                },
                {
                    "wf": "июн",
                    "wtype": "word",
                    "off_start": 3,
                    "off_end": 6,
                    "next_word": 2,
                    "sentence_index": 1,
                    "sentence_index_neg": 8
                },
                {
                    "wf": "—",
                    "wtype": "word",
                    "off_start": 7,
                    "off_end": 8,
                    "next_word": 3,
                    "sentence_index": 2,
                    "sentence_index_neg": 7,
                    "ana": [
                        {
                            "lex": "—",
                            "gr.tags": [
                                "guio"
                            ],
                            "trans_ru": "—"
                        }
                    ]
                },
                {
                    "wf": "Антонио",
                    "wtype": "word",
                    "off_start": 9,
                    "off_end": 16,
                    "next_word": 4,
                    "sentence_index": 3,
                    "sentence_index_neg": 6
                },
                {
                    "wf": "Гауди",
                    "wtype": "word",
                    "off_start": 17,
                    "off_end": 22,
                    "next_word": 5,
                    "sentence_index": 4,
                    "sentence_index_neg": 5
                },
                {
                    "wf": ",",
                    "wtype": "punct",
                    "off_start": 23,
                    "off_end": 24,
                    "next_word": 6
                },
                {
                    "wf": "испан",
                    "wtype": "word",
                    "off_start": 25,
                    "off_end": 30,
                    "next_word": 7,
                    "sentence_index": 5,
                    "sentence_index_neg": 4
                },
                {
                    "wf": "архитектор",
                    "wtype": "word",
                    "off_start": 31,
                    "off_end": 41,
                    "next_word": 8,
                    "sentence_index": 6,
                    "sentence_index_neg": 3
                },
                {
                    "wf": "(",
                    "wtype": "punct",
                    "off_start": 42,
                    "off_end": 43,
                    "next_word": 9
                },
                {
                    "wf": "хв",
                    "wtype": "word",
                    "off_start": 44,
                    "off_end": 46,
                    "next_word": 10,
                    "sentence_index": 7,
                    "sentence_index_neg": 2
                },
                {
                    "wf": ".",
                    "wtype": "punct",
                    "off_start": 47,
                    "off_end": 48,
                    "next_word": null
                }
            ],
            "lang": 0
        },
        {
            "text": "1926 ) .",
            "words": [
                {
                    "wf": "1926",
                    "wtype": "word",
                    "off_start": 0,
                    "off_end": 4,
                    "next_word": 1,
                    "sentence_index": 0,
                    "sentence_index_neg": 2,
                    "ana": [
                        {
                            "lex": "1926",
                            "trans_ru": "1926",
                            "gr.pos": "num"
                        }
                    ]
                },
                {
                    "wf": ")",
                    "wtype": "punct",
                    "off_start": 5,
                    "off_end": 6,
                    "next_word": 2
                },
                {
                    "wf": ".",
                    "wtype": "punct",
                    "off_start": 7,
                    "off_end": 8,
                    "next_word": null
                }
            ],
            "lang": 0
        }
    ]
}