{
    "meta": {
        "filename": "wiki_20 апрель.json",
        "title": "20 апрель",
        "author": "",
        "year": "2020",
        "recplace": "",
        "genre": "nonfiction"
    },
    "sentences": [
        {
            "text": "20-абилеб Апрел — григорианияб календаралда рекъон лъагӀалил 110-абилеб къо ( високоснияб соналъ — 111-абилеб ) .",
            "words": [
                {
                    "wf": "20-абилеб",
                    "wtype": "word",
                    "off_start": 0,
                    "off_end": 9,
                    "next_word": 1,
                    "sentence_index": 0,
                    "sentence_index_neg": 15,
                    "ana": [
                        {
                            "lex": "20",
                            "gr.tags": [],
                            "trans_ru": "20",
                            "gr.prontype": "ord",
                            "gr.pos": "num",
                            "gr.gender": "nt"
                        }
                    ]
                },
                {
                    "wf": "Апрел",
                    "wtype": "word",
                    "off_start": 10,
                    "off_end": 15,
                    "next_word": 2,
                    "sentence_index": 1,
                    "sentence_index_neg": 14
                },
                {
                    "wf": "—",
                    "wtype": "word",
                    "off_start": 16,
                    "off_end": 17,
                    "next_word": 3,
                    "sentence_index": 2,
                    "sentence_index_neg": 13,
                    "ana": [
                        {
                            "lex": "—",
                            "gr.tags": [
                                "guio"
                            ],
                            "trans_ru": "—"
                        }
                    ]
                },
                {
                    "wf": "григорианияб",
                    "wtype": "word",
                    "off_start": 18,
                    "off_end": 30,
                    "next_word": 4,
                    "sentence_index": 3,
                    "sentence_index_neg": 12
                },
                {
                    "wf": "календаралда",
                    "wtype": "word",
                    "off_start": 31,
                    "off_end": 43,
                    "next_word": 5,
                    "sentence_index": 4,
                    "sentence_index_neg": 11,
                    "ana": [
                        {
                            "lex": "календарь",
                            "gr.tags": [],
                            "trans_ru": "календарь",
                            "gr.case": "loc",
                            "gr.pos": "n",
                            "gr.num": "sg",
                            "gr.gender": "nt"
                        }
                    ]
                },
                {
                    "wf": "рекъон",
                    "wtype": "word",
                    "off_start": 44,
                    "off_end": 50,
                    "next_word": 6,
                    "sentence_index": 5,
                    "sentence_index_neg": 10,
                    "ana": [
                        {
                            "lex": "рекъон",
                            "gr.tags": [],
                            "trans_ru": "согласно",
                            "gr.pos": "post"
                        }
                    ]
                },
                {
                    "wf": "лъагӀалил",
                    "wtype": "word",
                    "off_start": 51,
                    "off_end": 60,
                    "next_word": 7,
                    "sentence_index": 6,
                    "sentence_index_neg": 9,
                    "ana": [
                        {
                            "lex": "лъагӏел",
                            "gr.tags": [],
                            "trans_ru": "год",
                            "gr.case": "gen",
                            "gr.pos": "n",
                            "gr.num": "sg",
                            "gr.gender": "nt"
                        }
                    ]
                },
                {
                    "wf": "110-абилеб",
                    "wtype": "word",
                    "off_start": 61,
                    "off_end": 71,
                    "next_word": 8,
                    "sentence_index": 7,
                    "sentence_index_neg": 8,
                    "ana": [
                        {
                            "lex": "110",
                            "gr.tags": [],
                            "trans_ru": "110",
                            "gr.prontype": "ord",
                            "gr.pos": "num",
                            "gr.gender": "nt"
                        }
                    ]
                },
                {
                    "wf": "къо",
                    "wtype": "word",
                    "off_start": 46,
                    "off_end": 49,
                    "next_word": 9,
                    "sentence_index": 8,
                    "sentence_index_neg": 7,
                    "ana": [
                        {
                            "lex": "къо",
                            "gr.tags": [],
                            "trans_ru": "день",
                            "gr.case": "nom",
                            "gr.pos": "n",
                            "gr.num": "sg",
                            "gr.gender": "nt"
                        }
                    ]
                },
                {
                    "wf": "(",
                    "wtype": "punct",
                    "off_start": 76,
                    "off_end": 77,
                    "next_word": 10
                },
                {
                    "wf": "високоснияб",
                    "wtype": "word",
                    "off_start": 78,
                    "off_end": 89,
                    "next_word": 11,
                    "sentence_index": 9,
                    "sentence_index_neg": 6
                },
                {
                    "wf": "соналъ",
                    "wtype": "word",
                    "off_start": 90,
                    "off_end": 96,
                    "next_word": 12,
                    "sentence_index": 10,
                    "sentence_index_neg": 5,
                    "ana": [
                        {
                            "lex": "сон",
                            "gr.tags": [],
                            "trans_ru": "год",
                            "gr.case": "erg",
                            "gr.pos": "n",
                            "gr.num": "sg",
                            "gr.gender": "nt"
                        }
                    ]
                },
                {
                    "wf": "—",
                    "wtype": "word",
                    "off_start": 16,
                    "off_end": 17,
                    "next_word": 13,
                    "sentence_index": 11,
                    "sentence_index_neg": 4,
                    "ana": [
                        {
                            "lex": "—",
                            "gr.tags": [
                                "guio"
                            ],
                            "trans_ru": "—"
                        }
                    ]
                },
                {
                    "wf": "111-абилеб",
                    "wtype": "word",
                    "off_start": 99,
                    "off_end": 109,
                    "next_word": 14,
                    "sentence_index": 12,
                    "sentence_index_neg": 3,
                    "ana": [
                        {
                            "lex": "111",
                            "gr.tags": [],
                            "trans_ru": "111",
                            "gr.prontype": "ord",
                            "gr.pos": "num",
                            "gr.gender": "nt"
                        }
                    ]
                },
                {
                    "wf": ")",
                    "wtype": "punct",
                    "off_start": 110,
                    "off_end": 111,
                    "next_word": 15
                },
                {
                    "wf": ".",
                    "wtype": "punct",
                    "off_start": 112,
                    "off_end": 113,
                    "next_word": null
                }
            ],
            "lang": 0,
            "meta": {
                "source": "Wikipedia",
                "date": "2020",
                "title": "20 апрель",
                "author": ""
            }
        },
        {
            "text": "ЛъагӀел сверизе хутӀула 255 къо .",
            "words": [
                {
                    "wf": "ЛъагӀел",
                    "wtype": "word",
                    "off_start": 0,
                    "off_end": 7,
                    "next_word": 1,
                    "sentence_index": 0,
                    "sentence_index_neg": 5,
                    "ana": [
                        {
                            "lex": "лъагӏел",
                            "gr.tags": [],
                            "trans_ru": "год",
                            "gr.case": "nom",
                            "gr.pos": "n",
                            "gr.num": "sg",
                            "gr.gender": "nt"
                        }
                    ]
                },
                {
                    "wf": "сверизе",
                    "wtype": "word",
                    "off_start": 8,
                    "off_end": 15,
                    "next_word": 2,
                    "sentence_index": 1,
                    "sentence_index_neg": 4,
                    "ana": [
                        {
                            "lex": "сверизе",
                            "gr.tags": [],
                            "trans_ru": "крутиться",
                            "gr.v_form": "inf",
                            "gr.transitivity": "iv",
                            "gr.pos": "vblex"
                        }
                    ]
                },
                {
                    "wf": "хутӀула",
                    "wtype": "word",
                    "off_start": 16,
                    "off_end": 23,
                    "next_word": 3,
                    "sentence_index": 2,
                    "sentence_index_neg": 3,
                    "ana": [
                        {
                            "lex": "хутӏизе",
                            "gr.tags": [],
                            "trans_ru": "остаться",
                            "gr.transitivity": "iv",
                            "gr.pos": "vblex",
                            "gr.tense": "aor"
                        }
                    ]
                },
                {
                    "wf": "255",
                    "wtype": "word",
                    "off_start": 24,
                    "off_end": 27,
                    "next_word": 4,
                    "sentence_index": 3,
                    "sentence_index_neg": 2,
                    "ana": [
                        {
                            "lex": "255",
                            "gr.tags": [],
                            "trans_ru": "255",
                            "gr.pos": "num"
                        }
                    ]
                },
                {
                    "wf": "къо",
                    "wtype": "word",
                    "off_start": 28,
                    "off_end": 31,
                    "next_word": 5,
                    "sentence_index": 4,
                    "sentence_index_neg": 1,
                    "ana": [
                        {
                            "lex": "къо",
                            "gr.tags": [],
                            "trans_ru": "день",
                            "gr.case": "nom",
                            "gr.pos": "n",
                            "gr.num": "sg",
                            "gr.gender": "nt"
                        }
                    ]
                },
                {
                    "wf": ".",
                    "wtype": "punct",
                    "off_start": 32,
                    "off_end": 33,
                    "next_word": null
                }
            ],
            "lang": 0,
            "meta": {
                "source": "Wikipedia",
                "date": "2020",
                "title": "20 апрель",
                "author": ""
            }
        },
        {
            "text": "Шахрулабазанов , ГӀабдурашид МухӀамадкамилил ( 1986 ) - дагъистаналъул бизнесмен .",
            "words": [
                {
                    "wf": "Шахрулабазанов",
                    "wtype": "word",
                    "off_start": 0,
                    "off_end": 14,
                    "next_word": 1,
                    "sentence_index": 0,
                    "sentence_index_neg": 8
                },
                {
                    "wf": ",",
                    "wtype": "punct",
                    "off_start": 15,
                    "off_end": 16,
                    "next_word": 2
                },
                {
                    "wf": "ГӀабдурашид",
                    "wtype": "word",
                    "off_start": 17,
                    "off_end": 28,
                    "next_word": 3,
                    "sentence_index": 1,
                    "sentence_index_neg": 7
                },
                {
                    "wf": "МухӀамадкамилил",
                    "wtype": "word",
                    "off_start": 29,
                    "off_end": 44,
                    "next_word": 4,
                    "sentence_index": 2,
                    "sentence_index_neg": 6,
                    "ana": [
                        {
                            "lex": "Мухӏамадкамил",
                            "gr.tags": [],
                            "trans_ru": "Мухӏамадкамил",
                            "gr.case": "gen",
                            "gr.nametype": "ant",
                            "gr.pos": "np",
                            "gr.gender": "m"
                        }
                    ]
                },
                {
                    "wf": "(",
                    "wtype": "punct",
                    "off_start": 45,
                    "off_end": 46,
                    "next_word": 5
                },
                {
                    "wf": "1986",
                    "wtype": "word",
                    "off_start": 47,
                    "off_end": 51,
                    "next_word": 6,
                    "sentence_index": 3,
                    "sentence_index_neg": 5,
                    "ana": [
                        {
                            "lex": "1986",
                            "gr.tags": [],
                            "trans_ru": "1986",
                            "gr.pos": "num"
                        }
                    ]
                },
                {
                    "wf": ")",
                    "wtype": "punct",
                    "off_start": 52,
                    "off_end": 53,
                    "next_word": 7
                },
                {
                    "wf": "-",
                    "wtype": "punct",
                    "off_start": 54,
                    "off_end": 55,
                    "next_word": 8
                },
                {
                    "wf": "дагъистаналъул",
                    "wtype": "word",
                    "off_start": 56,
                    "off_end": 70,
                    "next_word": 9,
                    "sentence_index": 4,
                    "sentence_index_neg": 4
                },
                {
                    "wf": "бизнесмен",
                    "wtype": "word",
                    "off_start": 71,
                    "off_end": 80,
                    "next_word": 10,
                    "sentence_index": 5,
                    "sentence_index_neg": 3,
                    "ana": [
                        {
                            "lex": "бизнесмен",
                            "gr.tags": [],
                            "trans_ru": "бизнесмен",
                            "gr.case": "nom",
                            "gr.pos": "n",
                            "gr.num": "sg",
                            "gr.gender": "m"
                        }
                    ]
                },
                {
                    "wf": ".",
                    "wtype": "punct",
                    "off_start": 81,
                    "off_end": 82,
                    "next_word": null
                }
            ],
            "lang": 0,
            "meta": {
                "source": "Wikipedia",
                "date": "2020",
                "title": "20 апрель",
                "author": ""
            }
        }
    ]
}