{
    "meta": {
        "filename": "wiki_Анцухъдерил сверел.json",
        "title": "Анцухъдерил сверел",
        "author": "",
        "year": "2020",
        "recplace": "",
        "genre": "nonfiction"
    },
    "sentences": [
        {
            "text": "Анцухъдерил сверел — авар мацӀалъул диалектазул цояб , жиб бакъдасеб тӀадгаруде гъорлӀе унеб .",
            "words": [
                {
                    "wf": "Анцухъдерил",
                    "wtype": "word",
                    "off_start": 0,
                    "off_end": 11,
                    "next_word": 1,
                    "sentence_index": 0,
                    "sentence_index_neg": 12
                },
                {
                    "wf": "сверел",
                    "wtype": "word",
                    "off_start": 12,
                    "off_end": 18,
                    "next_word": 2,
                    "sentence_index": 1,
                    "sentence_index_neg": 11
                },
                {
                    "wf": "—",
                    "wtype": "word",
                    "off_start": 19,
                    "off_end": 20,
                    "next_word": 3,
                    "sentence_index": 2,
                    "sentence_index_neg": 10,
                    "ana": [
                        {
                            "lex": "—",
                            "gr.tags": [
                                "guio"
                            ],
                            "trans_ru": "—"
                        }
                    ]
                },
                {
                    "wf": "авар",
                    "wtype": "word",
                    "off_start": 21,
                    "off_end": 25,
                    "next_word": 4,
                    "sentence_index": 3,
                    "sentence_index_neg": 9,
                    "ana": [
                        {
                            "lex": "авар",
                            "trans_ru": "аварский",
                            "gr.pos": "adj"
                        }
                    ]
                },
                {
                    "wf": "мацӀалъул",
                    "wtype": "word",
                    "off_start": 26,
                    "off_end": 35,
                    "next_word": 5,
                    "sentence_index": 4,
                    "sentence_index_neg": 8,
                    "ana": [
                        {
                            "lex": "мацӏ",
                            "trans_ru": "язык",
                            "gr.case": "gen",
                            "gr.pos": "n",
                            "gr.num": "sg",
                            "gr.gender": "nt"
                        }
                    ]
                },
                {
                    "wf": "диалектазул",
                    "wtype": "word",
                    "off_start": 36,
                    "off_end": 47,
                    "next_word": 6,
                    "sentence_index": 5,
                    "sentence_index_neg": 7,
                    "ana": [
                        {
                            "lex": "диалект",
                            "trans_ru": "диалект",
                            "gr.case": "gen",
                            "gr.pos": "n",
                            "gr.num": "pl",
                            "gr.gender": "nt"
                        }
                    ]
                },
                {
                    "wf": "цояб",
                    "wtype": "word",
                    "off_start": 48,
                    "off_end": 52,
                    "next_word": 7,
                    "sentence_index": 6,
                    "sentence_index_neg": 6,
                    "ana": [
                        {
                            "lex": "цо",
                            "trans_ru": "один",
                            "gr.other": "subst",
                            "gr.case": "nom",
                            "gr.pos": "num",
                            "gr.num": "sg",
                            "gr.gender": "nt"
                        }
                    ]
                },
                {
                    "wf": ",",
                    "wtype": "punct",
                    "off_start": 53,
                    "off_end": 54,
                    "next_word": 8
                },
                {
                    "wf": "жиб",
                    "wtype": "word",
                    "off_start": 55,
                    "off_end": 58,
                    "next_word": 9,
                    "sentence_index": 7,
                    "sentence_index_neg": 5,
                    "ana": [
                        {
                            "lex": "жиб",
                            "trans_ru": "сам",
                            "gr.prontype": "ref",
                            "gr.case": "nom",
                            "gr.pos": "prn",
                            "gr.num": "sg",
                            "gr.gender": "nt"
                        }
                    ]
                },
                {
                    "wf": "бакъдасеб",
                    "wtype": "word",
                    "off_start": 59,
                    "off_end": 68,
                    "next_word": 10,
                    "sentence_index": 8,
                    "sentence_index_neg": 4
                },
                {
                    "wf": "тӀадгаруде",
                    "wtype": "word",
                    "off_start": 69,
                    "off_end": 79,
                    "next_word": 11,
                    "sentence_index": 9,
                    "sentence_index_neg": 3
                },
                {
                    "wf": "гъорлӀе",
                    "wtype": "word",
                    "off_start": 80,
                    "off_end": 87,
                    "next_word": 12,
                    "sentence_index": 10,
                    "sentence_index_neg": 2
                },
                {
                    "wf": "унеб",
                    "wtype": "word",
                    "off_start": 88,
                    "off_end": 92,
                    "next_word": 13,
                    "sentence_index": 11,
                    "sentence_index_neg": 1,
                    "ana": [
                        {
                            "lex": "ине",
                            "trans_ru": "идти",
                            "gr.v_form_ptcp": "gpr1",
                            "gr.transitivity": "iv",
                            "gr.pos": "vblex",
                            "gr.gender": "nt"
                        }
                    ]
                },
                {
                    "wf": ".",
                    "wtype": "punct",
                    "off_start": 93,
                    "off_end": 94,
                    "next_word": null
                }
            ],
            "lang": 0,
            "meta": {
                "source": "Wikipedia",
                "date": "2020",
                "title": "Ал-ХӀакиму",
                "author": ""
            }
        },
        {
            "text": "Сверел буго тӀибитӀун ЛъаратӀа мухъалда ; бикьула щуго гаргаралде .",
            "words": [
                {
                    "wf": "Сверел",
                    "wtype": "word",
                    "off_start": 0,
                    "off_end": 6,
                    "next_word": 1,
                    "sentence_index": 0,
                    "sentence_index_neg": 9
                },
                {
                    "wf": "буго",
                    "wtype": "word",
                    "off_start": 7,
                    "off_end": 11,
                    "next_word": 2,
                    "sentence_index": 1,
                    "sentence_index_neg": 8,
                    "ana": [
                        {
                            "lex": "букӏине",
                            "trans_ru": "быть",
                            "gr.transitivity": "iv",
                            "gr.pos": "vblex",
                            "gr.tense": "pres",
                            "gr.gender": "nt"
                        }
                    ]
                },
                {
                    "wf": "тӀибитӀун",
                    "wtype": "word",
                    "off_start": 12,
                    "off_end": 21,
                    "next_word": 3,
                    "sentence_index": 2,
                    "sentence_index_neg": 7,
                    "ana": [
                        {
                            "lex": "тӏибитӏизе",
                            "trans_ru": "тӏибитӏизе",
                            "gr.transitivity": "iv",
                            "gr.pos": "vblex",
                            "gr.v_form_cvb": "gna2",
                            "gr.gender": "nt"
                        }
                    ]
                },
                {
                    "wf": "ЛъаратӀа",
                    "wtype": "word",
                    "off_start": 22,
                    "off_end": 30,
                    "next_word": 4,
                    "sentence_index": 3,
                    "sentence_index_neg": 6,
                    "ana": [
                        {
                            "lex": "Лъаратӏа",
                            "trans_ru": "Лъаратӏа",
                            "gr.case": "nom",
                            "gr.nametype": "top",
                            "gr.pos": "np",
                            "gr.num": "sg"
                        },
                        {
                            "lex": "Лъаратӏа",
                            "trans_ru": "Лъаратӏа",
                            "gr.other": "attr",
                            "gr.nametype": "top",
                            "gr.pos": "np",
                            "gr.num": "sg"
                        }
                    ]
                },
                {
                    "wf": "мухъалда",
                    "wtype": "word",
                    "off_start": 31,
                    "off_end": 39,
                    "next_word": 5,
                    "sentence_index": 4,
                    "sentence_index_neg": 5,
                    "ana": [
                        {
                            "lex": "мухъ",
                            "trans_ru": "край",
                            "gr.case": "loc",
                            "gr.pos": "n",
                            "gr.num": "sg",
                            "gr.gender": "nt"
                        }
                    ]
                },
                {
                    "wf": ";",
                    "wtype": "punct",
                    "off_start": 40,
                    "off_end": 41,
                    "next_word": 6
                },
                {
                    "wf": "бикьула",
                    "wtype": "word",
                    "off_start": 42,
                    "off_end": 49,
                    "next_word": 7,
                    "sentence_index": 5,
                    "sentence_index_neg": 4,
                    "ana": [
                        {
                            "lex": "бикьизе",
                            "trans_ru": "делиться",
                            "gr.transitivity": "iv",
                            "gr.pos": "vblex",
                            "gr.tense": "aor",
                            "gr.gender": "nt"
                        }
                    ]
                },
                {
                    "wf": "щуго",
                    "wtype": "word",
                    "off_start": 50,
                    "off_end": 54,
                    "next_word": 8,
                    "sentence_index": 6,
                    "sentence_index_neg": 3,
                    "ana": [
                        {
                            "lex": "щуго",
                            "trans_ru": "пять",
                            "gr.pos": "num"
                        }
                    ]
                },
                {
                    "wf": "гаргаралде",
                    "wtype": "word",
                    "off_start": 55,
                    "off_end": 65,
                    "next_word": 9,
                    "sentence_index": 7,
                    "sentence_index_neg": 2
                },
                {
                    "wf": ".",
                    "wtype": "punct",
                    "off_start": 66,
                    "off_end": 67,
                    "next_word": null
                }
            ],
            "lang": 0,
            "meta": {
                "source": "Wikipedia",
                "date": "2020",
                "title": "Ал-ХӀакиму",
                "author": ""
            }
        },
        {
            "text": "Анцухъдерил свералил тӀибитӀул ареал ккола гьанжесеб ЛъаратӀа мухъ .",
            "words": [
                {
                    "wf": "Анцухъдерил",
                    "wtype": "word",
                    "off_start": 0,
                    "off_end": 11,
                    "next_word": 1,
                    "sentence_index": 0,
                    "sentence_index_neg": 8
                },
                {
                    "wf": "свералил",
                    "wtype": "word",
                    "off_start": 12,
                    "off_end": 20,
                    "next_word": 2,
                    "sentence_index": 1,
                    "sentence_index_neg": 7
                },
                {
                    "wf": "тӀибитӀул",
                    "wtype": "word",
                    "off_start": 21,
                    "off_end": 30,
                    "next_word": 3,
                    "sentence_index": 2,
                    "sentence_index_neg": 6
                },
                {
                    "wf": "ареал",
                    "wtype": "word",
                    "off_start": 31,
                    "off_end": 36,
                    "next_word": 4,
                    "sentence_index": 3,
                    "sentence_index_neg": 5
                },
                {
                    "wf": "ккола",
                    "wtype": "word",
                    "off_start": 37,
                    "off_end": 42,
                    "next_word": 5,
                    "sentence_index": 4,
                    "sentence_index_neg": 4,
                    "ana": [
                        {
                            "lex": "кквезе",
                            "trans_ru": "держаться",
                            "gr.transitivity": "iv",
                            "gr.pos": "vblex",
                            "gr.tense": "aor"
                        },
                        {
                            "lex": "ккезе",
                            "trans_ru": "оказываться",
                            "gr.transitivity": "iv",
                            "gr.pos": "vblex",
                            "gr.tense": "aor"
                        }
                    ]
                },
                {
                    "wf": "гьанжесеб",
                    "wtype": "word",
                    "off_start": 43,
                    "off_end": 52,
                    "next_word": 6,
                    "sentence_index": 5,
                    "sentence_index_neg": 3,
                    "ana": [
                        {
                            "lex": "гьанжесеб",
                            "trans_ru": "теперешный",
                            "gr.pos": "adj",
                            "gr.gender": "nt"
                        }
                    ]
                },
                {
                    "wf": "ЛъаратӀа",
                    "wtype": "word",
                    "off_start": 53,
                    "off_end": 61,
                    "next_word": 7,
                    "sentence_index": 6,
                    "sentence_index_neg": 2,
                    "ana": [
                        {
                            "lex": "Лъаратӏа",
                            "trans_ru": "Лъаратӏа",
                            "gr.other": "attr",
                            "gr.nametype": "top",
                            "gr.pos": "np",
                            "gr.num": "sg"
                        },
                        {
                            "lex": "Лъаратӏа",
                            "trans_ru": "Лъаратӏа",
                            "gr.case": "nom",
                            "gr.nametype": "top",
                            "gr.pos": "np",
                            "gr.num": "sg"
                        }
                    ]
                },
                {
                    "wf": "мухъ",
                    "wtype": "word",
                    "off_start": 62,
                    "off_end": 66,
                    "next_word": 8,
                    "sentence_index": 7,
                    "sentence_index_neg": 1,
                    "ana": [
                        {
                            "lex": "мухъ",
                            "trans_ru": "край",
                            "gr.case": "nom",
                            "gr.pos": "n",
                            "gr.num": "sg",
                            "gr.gender": "nt"
                        }
                    ]
                },
                {
                    "wf": ".",
                    "wtype": "punct",
                    "off_start": 67,
                    "off_end": 68,
                    "next_word": null
                }
            ],
            "lang": 0,
            "meta": {
                "source": "Wikipedia",
                "date": "2020",
                "title": "Ал-ХӀакиму",
                "author": ""
            }
        },
        {
            "text": "Мадугьалихъ руго хьондехун къелесезул жубараб гаргар , бакъаккудехун — къаралазулги гьочотӀисезулги , бакъдехун — закаталисезул сверел .",
            "words": [
                {
                    "wf": "Мадугьалихъ",
                    "wtype": "word",
                    "off_start": 0,
                    "off_end": 11,
                    "next_word": 1,
                    "sentence_index": 0,
                    "sentence_index_neg": 14,
                    "ana": [
                        {
                            "lex": "мадугьалихъ",
                            "trans_ru": "в соседстве",
                            "gr.case": "loc",
                            "gr.pos": "adv"
                        }
                    ]
                },
                {
                    "wf": "руго",
                    "wtype": "word",
                    "off_start": 12,
                    "off_end": 16,
                    "next_word": 2,
                    "sentence_index": 1,
                    "sentence_index_neg": 13,
                    "ana": [
                        {
                            "lex": "букӏине",
                            "trans_ru": "быть",
                            "gr.transitivity": "iv",
                            "gr.pos": "vblex",
                            "gr.tense": "pres",
                            "gr.num": "pl"
                        }
                    ]
                },
                {
                    "wf": "хьондехун",
                    "wtype": "word",
                    "off_start": 17,
                    "off_end": 26,
                    "next_word": 3,
                    "sentence_index": 2,
                    "sentence_index_neg": 12
                },
                {
                    "wf": "къелесезул",
                    "wtype": "word",
                    "off_start": 27,
                    "off_end": 37,
                    "next_word": 4,
                    "sentence_index": 3,
                    "sentence_index_neg": 11
                },
                {
                    "wf": "жубараб",
                    "wtype": "word",
                    "off_start": 38,
                    "off_end": 45,
                    "next_word": 5,
                    "sentence_index": 4,
                    "sentence_index_neg": 10,
                    "ana": [
                        {
                            "lex": "жубазе",
                            "trans_ru": "жубазе",
                            "gr.v_form_ptcp": "gpr2",
                            "gr.transitivity": "iv",
                            "gr.pos": "vblex",
                            "gr.gender": "nt"
                        }
                    ]
                },
                {
                    "wf": "гаргар",
                    "wtype": "word",
                    "off_start": 46,
                    "off_end": 52,
                    "next_word": 6,
                    "sentence_index": 5,
                    "sentence_index_neg": 9
                },
                {
                    "wf": ",",
                    "wtype": "punct",
                    "off_start": 53,
                    "off_end": 54,
                    "next_word": 7
                },
                {
                    "wf": "бакъаккудехун",
                    "wtype": "word",
                    "off_start": 55,
                    "off_end": 68,
                    "next_word": 8,
                    "sentence_index": 6,
                    "sentence_index_neg": 8
                },
                {
                    "wf": "—",
                    "wtype": "word",
                    "off_start": 69,
                    "off_end": 70,
                    "next_word": 9,
                    "sentence_index": 7,
                    "sentence_index_neg": 7,
                    "ana": [
                        {
                            "lex": "—",
                            "gr.tags": [
                                "guio"
                            ],
                            "trans_ru": "—"
                        }
                    ]
                },
                {
                    "wf": "къаралазулги",
                    "wtype": "word",
                    "off_start": 71,
                    "off_end": 83,
                    "next_word": 10,
                    "sentence_index": 8,
                    "sentence_index_neg": 6
                },
                {
                    "wf": "гьочотӀисезулги",
                    "wtype": "word",
                    "off_start": 84,
                    "off_end": 99,
                    "next_word": 11,
                    "sentence_index": 9,
                    "sentence_index_neg": 5
                },
                {
                    "wf": ",",
                    "wtype": "punct",
                    "off_start": 53,
                    "off_end": 54,
                    "next_word": 12
                },
                {
                    "wf": "бакъдехун",
                    "wtype": "word",
                    "off_start": 102,
                    "off_end": 111,
                    "next_word": 13,
                    "sentence_index": 10,
                    "sentence_index_neg": 4
                },
                {
                    "wf": "—",
                    "wtype": "word",
                    "off_start": 69,
                    "off_end": 70,
                    "next_word": 14,
                    "sentence_index": 11,
                    "sentence_index_neg": 3,
                    "ana": [
                        {
                            "lex": "—",
                            "gr.tags": [
                                "guio"
                            ],
                            "trans_ru": "—"
                        }
                    ]
                },
                {
                    "wf": "закаталисезул",
                    "wtype": "word",
                    "off_start": 114,
                    "off_end": 127,
                    "next_word": 15,
                    "sentence_index": 12,
                    "sentence_index_neg": 2
                },
                {
                    "wf": "сверел",
                    "wtype": "word",
                    "off_start": 128,
                    "off_end": 134,
                    "next_word": 16,
                    "sentence_index": 13,
                    "sentence_index_neg": 1
                },
                {
                    "wf": ".",
                    "wtype": "punct",
                    "off_start": 135,
                    "off_end": 136,
                    "next_word": null
                }
            ],
            "lang": 0,
            "meta": {
                "source": "Wikipedia",
                "date": "2020",
                "title": "Ал-ХӀакиму",
                "author": ""
            }
        },
        {
            "text": "СвералилӀ руго хадусел гаргарал : тӀомуразул , бухӀнадерил , кьаналазул , ташазул , анцӀросазул , чӀадаколосезул ) .",
            "words": [
                {
                    "wf": "СвералилӀ",
                    "wtype": "word",
                    "off_start": 0,
                    "off_end": 9,
                    "next_word": 1,
                    "sentence_index": 0,
                    "sentence_index_neg": 12
                },
                {
                    "wf": "руго",
                    "wtype": "word",
                    "off_start": 10,
                    "off_end": 14,
                    "next_word": 2,
                    "sentence_index": 1,
                    "sentence_index_neg": 11,
                    "ana": [
                        {
                            "lex": "букӏине",
                            "trans_ru": "быть",
                            "gr.transitivity": "iv",
                            "gr.pos": "vblex",
                            "gr.tense": "pres",
                            "gr.num": "pl"
                        }
                    ]
                },
                {
                    "wf": "хадусел",
                    "wtype": "word",
                    "off_start": 15,
                    "off_end": 22,
                    "next_word": 3,
                    "sentence_index": 2,
                    "sentence_index_neg": 10,
                    "ana": [
                        {
                            "lex": "хадусеб",
                            "trans_ru": "следовать",
                            "gr.pos": "adj",
                            "gr.num": "pl"
                        }
                    ]
                },
                {
                    "wf": "гаргарал",
                    "wtype": "word",
                    "off_start": 23,
                    "off_end": 31,
                    "next_word": 4,
                    "sentence_index": 3,
                    "sentence_index_neg": 9
                },
                {
                    "wf": ":",
                    "wtype": "punct",
                    "off_start": 32,
                    "off_end": 33,
                    "next_word": 5
                },
                {
                    "wf": "тӀомуразул",
                    "wtype": "word",
                    "off_start": 34,
                    "off_end": 44,
                    "next_word": 6,
                    "sentence_index": 4,
                    "sentence_index_neg": 8
                },
                {
                    "wf": ",",
                    "wtype": "punct",
                    "off_start": 45,
                    "off_end": 46,
                    "next_word": 7
                },
                {
                    "wf": "бухӀнадерил",
                    "wtype": "word",
                    "off_start": 47,
                    "off_end": 58,
                    "next_word": 8,
                    "sentence_index": 5,
                    "sentence_index_neg": 7
                },
                {
                    "wf": ",",
                    "wtype": "punct",
                    "off_start": 45,
                    "off_end": 46,
                    "next_word": 9
                },
                {
                    "wf": "кьаналазул",
                    "wtype": "word",
                    "off_start": 61,
                    "off_end": 71,
                    "next_word": 10,
                    "sentence_index": 6,
                    "sentence_index_neg": 6
                },
                {
                    "wf": ",",
                    "wtype": "punct",
                    "off_start": 45,
                    "off_end": 46,
                    "next_word": 11
                },
                {
                    "wf": "ташазул",
                    "wtype": "word",
                    "off_start": 74,
                    "off_end": 81,
                    "next_word": 12,
                    "sentence_index": 7,
                    "sentence_index_neg": 5
                },
                {
                    "wf": ",",
                    "wtype": "punct",
                    "off_start": 45,
                    "off_end": 46,
                    "next_word": 13
                },
                {
                    "wf": "анцӀросазул",
                    "wtype": "word",
                    "off_start": 84,
                    "off_end": 95,
                    "next_word": 14,
                    "sentence_index": 8,
                    "sentence_index_neg": 4
                },
                {
                    "wf": ",",
                    "wtype": "punct",
                    "off_start": 45,
                    "off_end": 46,
                    "next_word": 15
                },
                {
                    "wf": "чӀадаколосезул",
                    "wtype": "word",
                    "off_start": 98,
                    "off_end": 112,
                    "next_word": 16,
                    "sentence_index": 9,
                    "sentence_index_neg": 3
                },
                {
                    "wf": ")",
                    "wtype": "punct",
                    "off_start": 113,
                    "off_end": 114,
                    "next_word": 17
                },
                {
                    "wf": ".",
                    "wtype": "punct",
                    "off_start": 115,
                    "off_end": 116,
                    "next_word": null
                }
            ],
            "lang": 0,
            "meta": {
                "source": "Wikipedia",
                "date": "2020",
                "title": "Ал-ХӀакиму",
                "author": ""
            }
        },
        {
            "text": "МикагӀилилазул , Ш. И . ( 1959 ) .",
            "words": [
                {
                    "wf": "МикагӀилилазул",
                    "wtype": "word",
                    "off_start": 0,
                    "off_end": 14,
                    "next_word": 1,
                    "sentence_index": 0,
                    "sentence_index_neg": 6
                },
                {
                    "wf": ",",
                    "wtype": "punct",
                    "off_start": 15,
                    "off_end": 16,
                    "next_word": 2
                },
                {
                    "wf": "Ш.",
                    "wtype": "word",
                    "off_start": 17,
                    "off_end": 19,
                    "next_word": 3,
                    "sentence_index": 1,
                    "sentence_index_neg": 5,
                    "ana": [
                        {
                            "lex": "Ш.",
                            "gr.tags": [
                                "\\<mf\\>attr"
                            ],
                            "trans_ru": "Ш.\\<mf\\>",
                            "gr.nametype": "ant",
                            "gr.pos": "np"
                        }
                    ]
                },
                {
                    "wf": "И",
                    "wtype": "word",
                    "off_start": 20,
                    "off_end": 21,
                    "next_word": 4,
                    "sentence_index": 2,
                    "sentence_index_neg": 4
                },
                {
                    "wf": ".",
                    "wtype": "punct",
                    "off_start": 18,
                    "off_end": 19,
                    "next_word": 5
                },
                {
                    "wf": "(",
                    "wtype": "punct",
                    "off_start": 24,
                    "off_end": 25,
                    "next_word": 6
                },
                {
                    "wf": "1959",
                    "wtype": "word",
                    "off_start": 26,
                    "off_end": 30,
                    "next_word": 7,
                    "sentence_index": 3,
                    "sentence_index_neg": 3,
                    "ana": [
                        {
                            "lex": "1959",
                            "trans_ru": "1959",
                            "gr.pos": "num"
                        }
                    ]
                },
                {
                    "wf": ")",
                    "wtype": "punct",
                    "off_start": 31,
                    "off_end": 32,
                    "next_word": 8
                },
                {
                    "wf": ".",
                    "wtype": "punct",
                    "off_start": 18,
                    "off_end": 19,
                    "next_word": null
                }
            ],
            "lang": 0,
            "meta": {
                "source": "Wikipedia",
                "date": "2020",
                "title": "Ал-ХӀакиму",
                "author": ""
            }
        },
        {
            "text": "\" Анцухский диалект Южного наречия \" \\[ Бакъдасеб тӀадгарул анцухъдерил сверел \\] .",
            "words": [
                {
                    "wf": "\"",
                    "wtype": "word",
                    "off_start": 0,
                    "off_end": 1,
                    "next_word": 1,
                    "sentence_index": 0,
                    "sentence_index_neg": 12,
                    "ana": [
                        {
                            "lex": "\"",
                            "gr.tags": [
                                "sent"
                            ],
                            "trans_ru": ""
                        }
                    ]
                },
                {
                    "wf": "Анцухский",
                    "wtype": "word",
                    "off_start": 2,
                    "off_end": 11,
                    "next_word": 2,
                    "sentence_index": 1,
                    "sentence_index_neg": 11
                },
                {
                    "wf": "диалект",
                    "wtype": "word",
                    "off_start": 12,
                    "off_end": 19,
                    "next_word": 3,
                    "sentence_index": 2,
                    "sentence_index_neg": 10,
                    "ana": [
                        {
                            "lex": "диалект",
                            "trans_ru": "диалект",
                            "gr.case": "nom",
                            "gr.pos": "n",
                            "gr.num": "sg",
                            "gr.gender": "nt"
                        }
                    ]
                },
                {
                    "wf": "Южного",
                    "wtype": "word",
                    "off_start": 20,
                    "off_end": 26,
                    "next_word": 4,
                    "sentence_index": 3,
                    "sentence_index_neg": 9
                },
                {
                    "wf": "наречия",
                    "wtype": "word",
                    "off_start": 27,
                    "off_end": 34,
                    "next_word": 5,
                    "sentence_index": 4,
                    "sentence_index_neg": 8
                },
                {
                    "wf": "\"",
                    "wtype": "word",
                    "off_start": 0,
                    "off_end": 1,
                    "next_word": 6,
                    "sentence_index": 5,
                    "sentence_index_neg": 7,
                    "ana": [
                        {
                            "lex": "\"",
                            "gr.tags": [
                                "sent"
                            ],
                            "trans_ru": ""
                        }
                    ]
                },
                {
                    "wf": "\\[",
                    "wtype": "word",
                    "off_start": 37,
                    "off_end": 39,
                    "next_word": 7,
                    "sentence_index": 6,
                    "sentence_index_neg": 6,
                    "ana": [
                        {
                            "lex": "\\[",
                            "gr.tags": [
                                "lpar"
                            ],
                            "trans_ru": "\\\\<sent>["
                        }
                    ]
                },
                {
                    "wf": "Бакъдасеб",
                    "wtype": "word",
                    "off_start": 40,
                    "off_end": 49,
                    "next_word": 8,
                    "sentence_index": 7,
                    "sentence_index_neg": 5
                },
                {
                    "wf": "тӀадгарул",
                    "wtype": "word",
                    "off_start": 50,
                    "off_end": 59,
                    "next_word": 9,
                    "sentence_index": 8,
                    "sentence_index_neg": 4
                },
                {
                    "wf": "анцухъдерил",
                    "wtype": "word",
                    "off_start": 60,
                    "off_end": 71,
                    "next_word": 10,
                    "sentence_index": 9,
                    "sentence_index_neg": 3
                },
                {
                    "wf": "сверел",
                    "wtype": "word",
                    "off_start": 72,
                    "off_end": 78,
                    "next_word": 11,
                    "sentence_index": 10,
                    "sentence_index_neg": 2
                },
                {
                    "wf": "\\]",
                    "wtype": "word",
                    "off_start": 79,
                    "off_end": 81,
                    "next_word": 12,
                    "sentence_index": 11,
                    "sentence_index_neg": 1,
                    "ana": [
                        {
                            "lex": "\\]",
                            "gr.tags": [
                                "rpar"
                            ],
                            "trans_ru": "\\\\<sent>]"
                        }
                    ]
                },
                {
                    "wf": ".",
                    "wtype": "punct",
                    "off_start": 82,
                    "off_end": 83,
                    "next_word": null
                }
            ],
            "lang": 0,
            "meta": {
                "source": "Wikipedia",
                "date": "2020",
                "title": "Ал-ХӀакиму",
                "author": ""
            }
        },
        {
            "text": "Бокарев , Е . А. ( ред . ) .",
            "words": [
                {
                    "wf": "Бокарев",
                    "wtype": "word",
                    "off_start": 0,
                    "off_end": 7,
                    "next_word": 1,
                    "sentence_index": 0,
                    "sentence_index_neg": 6
                },
                {
                    "wf": ",",
                    "wtype": "punct",
                    "off_start": 8,
                    "off_end": 9,
                    "next_word": 2
                },
                {
                    "wf": "Е",
                    "wtype": "word",
                    "off_start": 10,
                    "off_end": 11,
                    "next_word": 3,
                    "sentence_index": 1,
                    "sentence_index_neg": 5
                },
                {
                    "wf": ".",
                    "wtype": "punct",
                    "off_start": 12,
                    "off_end": 13,
                    "next_word": 4
                },
                {
                    "wf": "А.",
                    "wtype": "word",
                    "off_start": 14,
                    "off_end": 16,
                    "next_word": 5,
                    "sentence_index": 2,
                    "sentence_index_neg": 4,
                    "ana": [
                        {
                            "lex": "А.",
                            "gr.tags": [
                                "\\<mf\\>attr"
                            ],
                            "trans_ru": "А.\\<mf\\>",
                            "gr.nametype": "ant",
                            "gr.pos": "np"
                        }
                    ]
                },
                {
                    "wf": "(",
                    "wtype": "punct",
                    "off_start": 17,
                    "off_end": 18,
                    "next_word": 6
                },
                {
                    "wf": "ред",
                    "wtype": "word",
                    "off_start": 19,
                    "off_end": 22,
                    "next_word": 7,
                    "sentence_index": 3,
                    "sentence_index_neg": 3
                },
                {
                    "wf": ".",
                    "wtype": "punct",
                    "off_start": 12,
                    "off_end": 13,
                    "next_word": 8
                },
                {
                    "wf": ")",
                    "wtype": "punct",
                    "off_start": 25,
                    "off_end": 26,
                    "next_word": 9
                },
                {
                    "wf": ".",
                    "wtype": "punct",
                    "off_start": 12,
                    "off_end": 13,
                    "next_word": null
                }
            ],
            "lang": 0,
            "meta": {
                "source": "Wikipedia",
                "date": "2020",
                "title": "Ал-ХӀакиму",
                "author": ""
            }
        },
        {
            "text": "Очерки аварской диалектологии \\[ Авар диалектологиялъул хъвай-хъвагӀаял \\] .",
            "words": [
                {
                    "wf": "Очерки",
                    "wtype": "word",
                    "off_start": 0,
                    "off_end": 6,
                    "next_word": 1,
                    "sentence_index": 0,
                    "sentence_index_neg": 8
                },
                {
                    "wf": "аварской",
                    "wtype": "word",
                    "off_start": 7,
                    "off_end": 15,
                    "next_word": 2,
                    "sentence_index": 1,
                    "sentence_index_neg": 7
                },
                {
                    "wf": "диалектологии",
                    "wtype": "word",
                    "off_start": 16,
                    "off_end": 29,
                    "next_word": 3,
                    "sentence_index": 2,
                    "sentence_index_neg": 6
                },
                {
                    "wf": "\\[",
                    "wtype": "word",
                    "off_start": 30,
                    "off_end": 32,
                    "next_word": 4,
                    "sentence_index": 3,
                    "sentence_index_neg": 5,
                    "ana": [
                        {
                            "lex": "\\[",
                            "gr.tags": [
                                "lpar"
                            ],
                            "trans_ru": "\\\\<sent>["
                        }
                    ]
                },
                {
                    "wf": "Авар",
                    "wtype": "word",
                    "off_start": 33,
                    "off_end": 37,
                    "next_word": 5,
                    "sentence_index": 4,
                    "sentence_index_neg": 4,
                    "ana": [
                        {
                            "lex": "авар",
                            "trans_ru": "аварский",
                            "gr.pos": "adj"
                        }
                    ]
                },
                {
                    "wf": "диалектологиялъул",
                    "wtype": "word",
                    "off_start": 38,
                    "off_end": 55,
                    "next_word": 6,
                    "sentence_index": 5,
                    "sentence_index_neg": 3
                },
                {
                    "wf": "хъвай-хъвагӀаял",
                    "wtype": "word",
                    "off_start": 56,
                    "off_end": 71,
                    "next_word": 7,
                    "sentence_index": 6,
                    "sentence_index_neg": 2,
                    "ana": [
                        {
                            "lex": "хъвай-хъвагӏай",
                            "trans_ru": "письменность",
                            "gr.case": "nom",
                            "gr.pos": "n",
                            "gr.num": "pl",
                            "gr.gender": "nt"
                        }
                    ]
                },
                {
                    "wf": "\\]",
                    "wtype": "word",
                    "off_start": 72,
                    "off_end": 74,
                    "next_word": 8,
                    "sentence_index": 7,
                    "sentence_index_neg": 1,
                    "ana": [
                        {
                            "lex": "\\]",
                            "gr.tags": [
                                "rpar"
                            ],
                            "trans_ru": "\\\\<sent>]"
                        }
                    ]
                },
                {
                    "wf": ".",
                    "wtype": "punct",
                    "off_start": 75,
                    "off_end": 76,
                    "next_word": null
                }
            ],
            "lang": 0,
            "meta": {
                "source": "Wikipedia",
                "date": "2020",
                "title": "Ал-ХӀакиму",
                "author": ""
            }
        },
        {
            "text": "Ленинград : СССРалъул гӀелмабазул академиялъул пресса . гь .",
            "words": [
                {
                    "wf": "Ленинград",
                    "wtype": "word",
                    "off_start": 0,
                    "off_end": 9,
                    "next_word": 1,
                    "sentence_index": 0,
                    "sentence_index_neg": 7
                },
                {
                    "wf": ":",
                    "wtype": "punct",
                    "off_start": 10,
                    "off_end": 11,
                    "next_word": 2
                },
                {
                    "wf": "СССРалъул",
                    "wtype": "word",
                    "off_start": 12,
                    "off_end": 21,
                    "next_word": 3,
                    "sentence_index": 1,
                    "sentence_index_neg": 6,
                    "ana": [
                        {
                            "lex": "СССР",
                            "trans_ru": "СССР",
                            "gr.case": "gen",
                            "gr.nametype": "top",
                            "gr.pos": "np",
                            "gr.num": "sg"
                        }
                    ]
                },
                {
                    "wf": "гӀелмабазул",
                    "wtype": "word",
                    "off_start": 22,
                    "off_end": 33,
                    "next_word": 4,
                    "sentence_index": 2,
                    "sentence_index_neg": 5,
                    "ana": [
                        {
                            "lex": "гӏелму",
                            "trans_ru": "наук",
                            "gr.case": "gen",
                            "gr.pos": "n",
                            "gr.num": "pl",
                            "gr.gender": "nt"
                        }
                    ]
                },
                {
                    "wf": "академиялъул",
                    "wtype": "word",
                    "off_start": 34,
                    "off_end": 46,
                    "next_word": 5,
                    "sentence_index": 3,
                    "sentence_index_neg": 4,
                    "ana": [
                        {
                            "lex": "академия",
                            "trans_ru": "академия",
                            "gr.case": "gen",
                            "gr.pos": "n",
                            "gr.num": "sg",
                            "gr.gender": "nt"
                        }
                    ]
                },
                {
                    "wf": "пресса",
                    "wtype": "word",
                    "off_start": 47,
                    "off_end": 53,
                    "next_word": 6,
                    "sentence_index": 4,
                    "sentence_index_neg": 3,
                    "ana": [
                        {
                            "lex": "пресса",
                            "trans_ru": "пресса",
                            "gr.case": "nom",
                            "gr.pos": "n",
                            "gr.num": "sg",
                            "gr.gender": "nt"
                        }
                    ]
                },
                {
                    "wf": ".",
                    "wtype": "punct",
                    "off_start": 54,
                    "off_end": 55,
                    "next_word": 7
                },
                {
                    "wf": "гь",
                    "wtype": "word",
                    "off_start": 56,
                    "off_end": 58,
                    "next_word": 8,
                    "sentence_index": 5,
                    "sentence_index_neg": 2
                },
                {
                    "wf": ".",
                    "wtype": "punct",
                    "off_start": 54,
                    "off_end": 55,
                    "next_word": null
                }
            ],
            "lang": 0,
            "meta": {
                "source": "Wikipedia",
                "date": "2020",
                "title": "Ал-ХӀакиму",
                "author": ""
            }
        },
        {
            "text": "510 .",
            "words": [
                {
                    "wf": "510",
                    "wtype": "word",
                    "off_start": 0,
                    "off_end": 3,
                    "next_word": 1,
                    "sentence_index": 0,
                    "sentence_index_neg": 1,
                    "ana": [
                        {
                            "lex": "510",
                            "trans_ru": "510",
                            "gr.pos": "num"
                        }
                    ]
                },
                {
                    "wf": ".",
                    "wtype": "punct",
                    "off_start": 4,
                    "off_end": 5,
                    "next_word": null
                }
            ],
            "lang": 0,
            "meta": {
                "source": "Wikipedia",
                "date": "2020",
                "title": "Ал-ХӀакиму",
                "author": ""
            }
        }
    ]
}